<root main_tree_to_execute="MainTree">

  <BehaviorTree ID="Navigation">
    <RecoveryNode number_of_retries="6" name="NavigateRecovery">
      <PipelineSequence name="NavigateWithReplanning">
        <RateController hz="1.0">
          <RecoveryNode number_of_retries="1" name="RecoveryComputePathToPose">
            <ComputePathToPose goal="{goal}" path="{path}" planner_id="GridBased"/>
            <ReactiveFallback name="ComputePathToPoseRecoveryFallback">
              <GoalUpdated/>
              <ClearEntireCostmap name="ClearGlobalCostmap-Context" service_name="global_costmap/clear_entirely_global_costmap"/>
            </ReactiveFallback>
          </RecoveryNode>
        </RateController>
        <RecoveryNode number_of_retries="1" name="FollowPath">
          <FollowPath path="{path}" controller_id="FollowPath"/>
          <ReactiveFallback name="FollowPathRecoveryFallback">
            <GoalUpdated/>
            <ClearEntireCostmap name="ClearLocalCostmap-Context" service_name="local_costmap/clear_entirely_local_costmap"/>
          </ReactiveFallback>
        </RecoveryNode>
      </PipelineSequence>
      <ReactiveFallback name="RecoveryFallback">
        <GoalUpdated/>
        <!-- <Message msg="HELP!"/>
        <Wait wait_duration="5"/> -->
        <RoundRobin name="RecoveryActions">
          <Sequence name="ClearingActions">
            <ClearEntireCostmap name="ClearLocalCostmap-Subtree" service_name="local_costmap/clear_entirely_local_costmap"/>
            <ClearEntireCostmap name="ClearGlobalCostmap-Subtree" service_name="global_costmap/clear_entirely_global_costmap"/>
          </Sequence>
          <Spin spin_dist="1.57"/>
          <Wait wait_duration="5"/>
          <BackUp backup_dist="0.15" backup_speed="0.025"/>
        </RoundRobin>
      </ReactiveFallback>
    </RecoveryNode>
  </BehaviorTree>

  <!-- <BehaviorTree ID="ComputePoseWithObj">
  </BehaviorTree> -->
    
  <BehaviorTree ID="MainTree">
    <SequenceStar name="root">
      <!-- <CreateROS2Node node_name="some_name" spin="false" node_handle="{ros_node}" namespace="robot1"/> -->
      <!-- <SetParam node_name="global_costmap/global_costmap" param="static_layer.enabled;true"/> -->
      <!-- <ChangeNodeStatus service_name="global_costmap/global_costmap/change_state" server_timeout="{server_timeout}" ros2_node="{node}" target_state="activate"/> -->
      
      <!-- <SetParam node_name="global_costmap/global_costmap" param="static_layer.enabled;true"/> -->
      <!-- <CalculateGoal input_position="1.0;2.0" output_msg="{goal}"/> -->
      <CalculateGoal input_position="3.0;1.0" output_msg="{goal}"/>
      <ReactiveFallback name="test">
        <GoalReached global_frame="map" robot_base_frame="base_link" goal= "{goal}"/>
        <SubTree ID="Navigation" node="node" server_timeout="server_timeout" bt_loop_duration="bt_loop_duration" goal="goal"/>
      </ReactiveFallback>
    </SequenceStar>
  </BehaviorTree>
</root>
